watchmen_storage_mysql/__init__.py
watchmen_storage_mysql/data_source_mysql.py
watchmen_storage_mysql/script_builder_mysql.py
watchmen_storage_mysql/storage_mysql.py
watchmen_storage_mysql/storage_mysql_configuration.py
watchmen_storage_mysql/table_creator.py
watchmen_storage_mysql/where_build.py
watchmen_storage_mysql-18.0.1.dist-info/METADATA
watchmen_storage_mysql-18.0.1.dist-info/WHEEL
watchmen_storage_mysql-18.0.1.dist-info/licenses/LICENSE
watchmen_storage_mysql-18.0.1.dist-info/RECORD
